starlight/__init__.py
starlight-0.0.1.dist-info/METADATA
starlight-0.0.1.dist-info/WHEEL
starlight-0.0.1.dist-info/top_level.txt
starlight-0.0.1.dist-info/RECORD
